drf_dark_shade/__init__.py
drf_dark_shade/renderers.py
drf_dark_shade/static/css/deep-forest.css
drf_dark_shade/templates/drf_dark_shade/deep-forest.html
drf_dark_shade-0.1.5.dist-info/LICENSE
drf_dark_shade-0.1.5.dist-info/METADATA
drf_dark_shade-0.1.5.dist-info/WHEEL
drf_dark_shade-0.1.5.dist-info/RECORD
